opentelemetry_instrumentation_rq/__init__.py
opentelemetry_instrumentation_rq/instrumentor.py
opentelemetry_instrumentation_rq/rq_attributes.py
opentelemetry_instrumentation_rq/utils.py
opentelemetry_instrumentation_rq-0.1.3.dist-info/METADATA
opentelemetry_instrumentation_rq-0.1.3.dist-info/WHEEL
opentelemetry_instrumentation_rq-0.1.3.dist-info/licenses/LICENSE
opentelemetry_instrumentation_rq-0.1.3.dist-info/RECORD
