Metadata-Version: 2.4
Name: opentelemetry_instrumentation_rq
Version: 0.1.3
Summary: OpenTelemetry instrumentation for python RQ library
Project-URL: Homepage, https://github.com/K-T-Ng/opentelemetry-instrumentation-rq
Project-URL: Issues, https://github.com/K-T-Ng/opentelemetry-instrumentation-rq/issues
Author-email: K-T-Ng <l19so18h13k10@gmail.com>
License-File: LICENSE
Classifier: Development Status :: 2 - Pre-Alpha
Classifier: Operating System :: OS Independent
Classifier: Operating System :: POSIX
Classifier: Operating System :: Unix
Classifier: Programming Language :: Python :: 3.8
Classifier: Programming Language :: Python :: 3.9
Classifier: Programming Language :: Python :: 3.10
Classifier: Programming Language :: Python :: 3.11
Classifier: Programming Language :: Python :: 3.12
Requires-Python: >=3.8
Requires-Dist: opentelemetry-api~=1.28
Requires-Dist: opentelemetry-instrumentation~=0.50b0
Requires-Dist: opentelemetry-sdk~=1.28
Requires-Dist: rq>=1.15
